nextcloudmonitor.py
nextcloudmonitor-1.5.0.dist-info/LICENSE
nextcloudmonitor-1.5.0.dist-info/METADATA
nextcloudmonitor-1.5.0.dist-info/WHEEL
nextcloudmonitor-1.5.0.dist-info/top_level.txt
nextcloudmonitor-1.5.0.dist-info/RECORD
