Metadata-Version: 2.1
Name: nextcloudmonitor
Version: 1.5.0
Summary: Python wrapper around nextcloud monitor api
License-File: LICENSE
Requires-Dist: requests
